INSTALL.rst
LICENSE
MANIFEST.in
README.rst
VERSION
requirements.txt
setup.py
tasks.py
src/FGAme/__init__.py
src/FGAme/__main__.py
src/FGAme/__meta__.py
src/FGAme/asset.py
src/FGAme/configuration.py
src/FGAme/input.py
src/FGAme/logger.py
src/FGAme/mainloop.py
src/FGAme/mathtools.py
src/FGAme/objects.py
src/FGAme/patch.py
src/FGAme/resources.py
src/FGAme/screen.py
src/FGAme/signals.py
src/FGAme/sound.py
src/FGAme/zero.py
src/FGAme.egg-info/PKG-INFO
src/FGAme.egg-info/SOURCES.txt
src/FGAme.egg-info/dependency_links.txt
src/FGAme.egg-info/not-zip-safe
src/FGAme.egg-info/requires.txt
src/FGAme.egg-info/top_level.txt
src/FGAme/actions/__init__.py
src/FGAme/actions/asyncbase.py
src/FGAme/actions/base.py
src/FGAme/app/__init__.py
src/FGAme/assets/images/python-logo.png
src/FGAme/assets/music/laser-blaster.wav
src/FGAme/assets/sfx/laser-blaster.wav
src/FGAme/backends/__init__.py
src/FGAme/backends/core.py
src/FGAme/backends/kivy_be.py
src/FGAme/backends/kivy_conf.py
src/FGAme/backends/pygame_be.py
src/FGAme/backends/pygame_conf.py
src/FGAme/backends/pygamegfx_be.py
src/FGAme/backends/pygamegfx_conf.py
src/FGAme/backends/pygamegl_be.py
src/FGAme/backends/pygamegl_conf.py
src/FGAme/backends/pyglet_be.py
src/FGAme/backends/pyglet_conf.py
src/FGAme/backends/qt5_be.py
src/FGAme/backends/qt5_conf.py
src/FGAme/backends/sdl2_be.py
src/FGAme/backends/sdl2_conf.py
src/FGAme/backends/sdl2cffi_be.py
src/FGAme/backends/sdl2cffi_conf.py
src/FGAme/backends/testing_be.py
src/FGAme/backends/testing_conf.py
src/FGAme/demos/__init__.py
src/FGAme/demos/__main__.py
src/FGAme/demos/games/__init__.py
src/FGAme/demos/games/flappy.py
src/FGAme/demos/games/pong.py
src/FGAme/demos/games/pong_class.py
src/FGAme/demos/games/pong_gas.py
src/FGAme/demos/games/pong_one_liner.py
src/FGAme/demos/integrations/__init__.py
src/FGAme/demos/integrations/kivy_app.py
src/FGAme/demos/old/games/__init__.py
src/FGAme/demos/old/games/_runall_.py
src/FGAme/demos/old/games/explosion.py
src/FGAme/demos/old/games/poly_intersection.py
src/FGAme/demos/simple/__init__.py
src/FGAme/demos/simple/_runall_.py
src/FGAme/demos/simple/collisions_aabb.py
src/FGAme/demos/simple/collsions_circle.py
